feature_flags_co/__init__.py
feature_flags_co/ffc_client.py
feature_flags_co/ffc_user.py
feature_flags_co-0.0.21.dist-info/LICENSE
feature_flags_co-0.0.21.dist-info/METADATA
feature_flags_co-0.0.21.dist-info/WHEEL
feature_flags_co-0.0.21.dist-info/top_level.txt
feature_flags_co-0.0.21.dist-info/RECORD
