Metadata-Version: 2.1
Name: feature-flags-co
Version: 0.0.21
Summary: A Python SDK for feature-flags.co project
Home-page: https://github.com/feature-flags-co/ffc-python-sdk
Author: Jiyun YANG
Author-email: jiyun.yang.work@gmail.com
License: UNKNOWN
Project-URL: Bug Tracker, https://github.com/feature-flags-co/ffc-python-sdk/issues
Platform: UNKNOWN
Classifier: Programming Language :: Python :: 3
Classifier: License :: OSI Approved :: MIT License
Classifier: Operating System :: OS Independent
Requires-Python: >=3.6
License-File: LICENSE
